[
  {
    "ContainingType": "WMS.API.Controllers.AnnouncementController",
    "Method": "GetAll",
    "RelativePath": "api/Announcement",
    "HttpMethod": "GET",
    "IsController": true,
    "Order": 0,
    "Parameters": [],
    "ReturnTypes": []
  },
  {
    "ContainingType": "WMS.API.Controllers.AnnouncementController",
    "Method": "Add",
    "RelativePath": "api/Announcement",
    "HttpMethod": "POST",
    "IsController": true,
    "Order": 0,
    "Parameters": [
      {
        "Name": "dto",
        "Type": "WMS.Application.DTOs.Announcement.AnnouncementDto",
        "IsRequired": true
      }
    ],
    "ReturnTypes": []
  },
  {
    "ContainingType": "WMS.API.Controllers.AnnouncementController",
    "Method": "Update",
    "RelativePath": "api/Announcement",
    "HttpMethod": "PUT",
    "IsController": true,
    "Order": 0,
    "Parameters": [
      {
        "Name": "dto",
        "Type": "WMS.Application.DTOs.Announcement.AnnouncementDto",
        "IsRequired": true
      }
    ],
    "ReturnTypes": []
  },
  {
    "ContainingType": "WMS.API.Controllers.AnnouncementController",
    "Method": "GetById",
    "RelativePath": "api/Announcement/{id}",
    "HttpMethod": "GET",
    "IsController": true,
    "Order": 0,
    "Parameters": [
      {
        "Name": "id",
        "Type": "System.Int32",
        "IsRequired": true
      }
    ],
    "ReturnTypes": []
  },
  {
    "ContainingType": "WMS.API.Controllers.AnnouncementController",
    "Method": "Delete",
    "RelativePath": "api/Announcement/{id}",
    "HttpMethod": "DELETE",
    "IsController": true,
    "Order": 0,
    "Parameters": [
      {
        "Name": "id",
        "Type": "System.Int32",
        "IsRequired": true
      }
    ],
    "ReturnTypes": []
  },
  {
    "ContainingType": "WMS.API.Controllers.AttendanceController",
    "Method": "GetAttendance",
    "RelativePath": "api/Attendance",
    "HttpMethod": "GET",
    "IsController": true,
    "Order": 0,
    "Parameters": [],
    "ReturnTypes": []
  },
  {
    "ContainingType": "WMS.API.Controllers.AttendanceController",
    "Method": "AddAttendance",
    "RelativePath": "api/Attendance",
    "HttpMethod": "POST",
    "IsController": true,
    "Order": 0,
    "Parameters": [
      {
        "Name": "attendanceDto",
        "Type": "WMS.Application.DTOs.Attendance.AttendanceDto",
        "IsRequired": true
      }
    ],
    "ReturnTypes": []
  },
  {
    "ContainingType": "WMS.API.Controllers.AttendanceController",
    "Method": "CheckIn",
    "RelativePath": "api/Attendance/checkin",
    "HttpMethod": "POST",
    "IsController": true,
    "Order": 0,
    "Parameters": [
      {
        "Name": "employeeId",
        "Type": "System.Int32",
        "IsRequired": false
      },
      {
        "Name": "workMode",
        "Type": "System.String",
        "IsRequired": false
      }
    ],
    "ReturnTypes": []
  },
  {
    "ContainingType": "WMS.API.Controllers.AttendanceController",
    "Method": "CheckOut",
    "RelativePath": "api/Attendance/checkout",
    "HttpMethod": "POST",
    "IsController": true,
    "Order": 0,
    "Parameters": [
      {
        "Name": "employeeId",
        "Type": "System.Int32",
        "IsRequired": false
      }
    ],
    "ReturnTypes": []
  },
  {
    "ContainingType": "WMS.API.Controllers.AttendanceController",
    "Method": "GetAttendanceByMonth",
    "RelativePath": "api/Attendance/employee/{employeeId}/month",
    "HttpMethod": "GET",
    "IsController": true,
    "Order": 0,
    "Parameters": [
      {
        "Name": "employeeId",
        "Type": "System.Int32",
        "IsRequired": true
      },
      {
        "Name": "month",
        "Type": "System.Int32",
        "IsRequired": false
      },
      {
        "Name": "year",
        "Type": "System.Int32",
        "IsRequired": false
      }
    ],
    "ReturnTypes": []
  },
  {
    "ContainingType": "WMS.API.Controllers.AttendanceController",
    "Method": "GetMyAttendance",
    "RelativePath": "api/Attendance/my-attendance",
    "HttpMethod": "GET",
    "IsController": true,
    "Order": 0,
    "Parameters": [],
    "ReturnTypes": []
  },
  {
    "ContainingType": "WMS.API.Controllers.AuditLogController",
    "Method": "GetAll",
    "RelativePath": "api/AuditLog",
    "HttpMethod": "GET",
    "IsController": true,
    "Order": 0,
    "Parameters": [],
    "ReturnTypes": []
  },
  {
    "ContainingType": "WMS.API.Controllers.AuditLogController",
    "Method": "Add",
    "RelativePath": "api/AuditLog",
    "HttpMethod": "POST",
    "IsController": true,
    "Order": 0,
    "Parameters": [
      {
        "Name": "auditLogDto",
        "Type": "WMS.Application.DTOs.AuditLog.AuditLogDto",
        "IsRequired": true
      }
    ],
    "ReturnTypes": []
  },
  {
    "ContainingType": "WMS.API.Controllers.AuthController",
    "Method": "Login",
    "RelativePath": "api/Auth/login",
    "HttpMethod": "POST",
    "IsController": true,
    "Order": 0,
    "Parameters": [
      {
        "Name": "loginDto",
        "Type": "WMS.Application.DTOs.Auth.LoginDto",
        "IsRequired": true
      }
    ],
    "ReturnTypes": []
  },
  {
    "ContainingType": "WMS.API.Controllers.ClientController",
    "Method": "GetAll",
    "RelativePath": "api/Client",
    "HttpMethod": "GET",
    "IsController": true,
    "Order": 0,
    "Parameters": [],
    "ReturnTypes": []
  },
  {
    "ContainingType": "WMS.API.Controllers.ClientController",
    "Method": "Add",
    "RelativePath": "api/Client",
    "HttpMethod": "POST",
    "IsController": true,
    "Order": 0,
    "Parameters": [
      {
        "Name": "clientDto",
        "Type": "WMS.Application.DTOs.Client.ClientDto",
        "IsRequired": true
      }
    ],
    "ReturnTypes": []
  },
  {
    "ContainingType": "WMS.API.Controllers.ClientController",
    "Method": "Update",
    "RelativePath": "api/Client",
    "HttpMethod": "PUT",
    "IsController": true,
    "Order": 0,
    "Parameters": [
      {
        "Name": "clientDto",
        "Type": "WMS.Application.DTOs.Client.ClientDto",
        "IsRequired": true
      }
    ],
    "ReturnTypes": []
  },
  {
    "ContainingType": "WMS.API.Controllers.ClientController",
    "Method": "GetById",
    "RelativePath": "api/Client/{id}",
    "HttpMethod": "GET",
    "IsController": true,
    "Order": 0,
    "Parameters": [
      {
        "Name": "id",
        "Type": "System.Int32",
        "IsRequired": true
      }
    ],
    "ReturnTypes": []
  },
  {
    "ContainingType": "WMS.API.Controllers.ClientController",
    "Method": "Delete",
    "RelativePath": "api/Client/{id}",
    "HttpMethod": "DELETE",
    "IsController": true,
    "Order": 0,
    "Parameters": [
      {
        "Name": "id",
        "Type": "System.Int32",
        "IsRequired": true
      }
    ],
    "ReturnTypes": []
  },
  {
    "ContainingType": "WMS.API.Controllers.DepartmentController",
    "Method": "GetAllDepartments",
    "RelativePath": "api/Department",
    "HttpMethod": "GET",
    "IsController": true,
    "Order": 0,
    "Parameters": [],
    "ReturnTypes": []
  },
  {
    "ContainingType": "WMS.API.Controllers.DepartmentController",
    "Method": "AddDepartment",
    "RelativePath": "api/Department",
    "HttpMethod": "POST",
    "IsController": true,
    "Order": 0,
    "Parameters": [
      {
        "Name": "departmentDto",
        "Type": "WMS.Application.DTOs.Department.DepartmentDto",
        "IsRequired": true
      }
    ],
    "ReturnTypes": []
  },
  {
    "ContainingType": "WMS.API.Controllers.EmployeeController",
    "Method": "GetAllEmployees",
    "RelativePath": "api/Employee",
    "HttpMethod": "GET",
    "IsController": true,
    "Order": 0,
    "Parameters": [],
    "ReturnTypes": []
  },
  {
    "ContainingType": "WMS.API.Controllers.EmployeeController",
    "Method": "AddEmployee",
    "RelativePath": "api/Employee",
    "HttpMethod": "POST",
    "IsController": true,
    "Order": 0,
    "Parameters": [
      {
        "Name": "employeeDto",
        "Type": "WMS.Application.DTOs.Employee.EmployeeDto",
        "IsRequired": true
      }
    ],
    "ReturnTypes": []
  },
  {
    "ContainingType": "WMS.API.Controllers.EmployeeController",
    "Method": "GetEmployeeById",
    "RelativePath": "api/Employee/{id}",
    "HttpMethod": "GET",
    "IsController": true,
    "Order": 0,
    "Parameters": [
      {
        "Name": "id",
        "Type": "System.Int32",
        "IsRequired": true
      }
    ],
    "ReturnTypes": []
  },
  {
    "ContainingType": "WMS.API.Controllers.EmployeeController",
    "Method": "DeleteEmployee",
    "RelativePath": "api/Employee/{id}",
    "HttpMethod": "DELETE",
    "IsController": true,
    "Order": 0,
    "Parameters": [
      {
        "Name": "id",
        "Type": "System.Int32",
        "IsRequired": true
      }
    ],
    "ReturnTypes": []
  },
  {
    "ContainingType": "WMS.API.Controllers.EmployeeController",
    "Method": "UpdateEmployee",
    "RelativePath": "api/Employee/{id}",
    "HttpMethod": "PUT",
    "IsController": true,
    "Order": 0,
    "Parameters": [
      {
        "Name": "id",
        "Type": "System.Int32",
        "IsRequired": true
      },
      {
        "Name": "employeeDto",
        "Type": "WMS.Application.DTOs.Employee.EmployeeDto",
        "IsRequired": true
      }
    ],
    "ReturnTypes": []
  },
  {
    "ContainingType": "WMS.API.Controllers.LeaveRequestController",
    "Method": "GetLeaveRequests",
    "RelativePath": "api/LeaveRequest",
    "HttpMethod": "GET",
    "IsController": true,
    "Order": 0,
    "Parameters": [],
    "ReturnTypes": []
  },
  {
    "ContainingType": "WMS.API.Controllers.LeaveRequestController",
    "Method": "AddLeaveRequest",
    "RelativePath": "api/LeaveRequest",
    "HttpMethod": "POST",
    "IsController": true,
    "Order": 0,
    "Parameters": [
      {
        "Name": "leaveRequestDto",
        "Type": "WMS.Application.DTOs.Leave.LeaveRequestDto",
        "IsRequired": true
      }
    ],
    "ReturnTypes": []
  },
  {
    "ContainingType": "WMS.API.Controllers.LeaveRequestController",
    "Method": "DeleteLeave",
    "RelativePath": "api/LeaveRequest/{id}",
    "HttpMethod": "DELETE",
    "IsController": true,
    "Order": 0,
    "Parameters": [
      {
        "Name": "id",
        "Type": "System.Int32",
        "IsRequired": true
      }
    ],
    "ReturnTypes": []
  },
  {
    "ContainingType": "WMS.API.Controllers.LeaveRequestController",
    "Method": "ApproveLeave",
    "RelativePath": "api/LeaveRequest/approve/{id}",
    "HttpMethod": "PUT",
    "IsController": true,
    "Order": 0,
    "Parameters": [
      {
        "Name": "id",
        "Type": "System.Int32",
        "IsRequired": true
      }
    ],
    "ReturnTypes": []
  },
  {
    "ContainingType": "WMS.API.Controllers.LeaveRequestController",
    "Method": "GetMyLeaves",
    "RelativePath": "api/LeaveRequest/my-leaves",
    "HttpMethod": "GET",
    "IsController": true,
    "Order": 0,
    "Parameters": [],
    "ReturnTypes": []
  },
  {
    "ContainingType": "WMS.API.Controllers.LeaveRequestController",
    "Method": "RejectLeave",
    "RelativePath": "api/LeaveRequest/reject/{id}",
    "HttpMethod": "PUT",
    "IsController": true,
    "Order": 0,
    "Parameters": [
      {
        "Name": "id",
        "Type": "System.Int32",
        "IsRequired": true
      }
    ],
    "ReturnTypes": []
  },
  {
    "ContainingType": "WMS.API.Controllers.ProjectController",
    "Method": "GetAllProjects",
    "RelativePath": "api/Project",
    "HttpMethod": "GET",
    "IsController": true,
    "Order": 0,
    "Parameters": [],
    "ReturnTypes": []
  },
  {
    "ContainingType": "WMS.API.Controllers.ProjectController",
    "Method": "AddProject",
    "RelativePath": "api/Project",
    "HttpMethod": "POST",
    "IsController": true,
    "Order": 0,
    "Parameters": [
      {
        "Name": "projectDto",
        "Type": "WMS.Application.DTOs.Project.ProjectDto",
        "IsRequired": true
      }
    ],
    "ReturnTypes": []
  }
]